README.rst
setup.py
python_sailsd.egg-info/PKG-INFO
python_sailsd.egg-info/SOURCES.txt
python_sailsd.egg-info/dependency_links.txt
python_sailsd.egg-info/top_level.txt
sailsd/__init__.py
sailsd/boat.py
sailsd/sailsd.py
sailsd/wind.py