Metadata-Version: 1.1
Name: python-sailsd
Version: 0.2.0
Summary: Python library to make interacting with the sailsd API easy
Home-page: https://github.com/sails-simulator/python-sailsd
Author: Louis Taylor
Author-email: louis@kragniz.eu
License: MIT
Platform: UNKNOWN
Classifier: Intended Audience :: Developers
Classifier: License :: OSI Approved :: MIT License
Classifier: Programming Language :: Python
Classifier: Programming Language :: Python :: 2.7
Classifier: Programming Language :: Python :: 3.4
Classifier: Programming Language :: Python :: 3.5
